{
  "parent": "builtin/entity",
  "display": {
    "thirdperson_righthand": {
      "translation": [0, 5, -9.75],
      "scale": [1, 1, 0.82]
    },
    "thirdperson_lefthand": {
      "translation": [0, 5, -9.75],
      "scale": [1, 1, 0.82]
    },
    "firstperson_righthand": {
      "translation": [-3.25, 9.75, -6]
    },
    "firstperson_lefthand": {
      "translation": [-3.25, 9.75, -6]
    },
    "ground": {
      "translation": [0, 3.5, 0],
      "scale": [0.75, 0.75, 0.75]
    },
    "gui": {
      "rotation": [30, -135, 0],
      "translation": [1, 1.5, 0],
      "scale": [0.56, 0.56, 0.56]
    },
    "fixed": {
      "rotation": [0, 90, 0],
      "translation": [-5.75, 7.75, -1],
      "scale": [1.5, 1.5, 1.5]
    }
  }
}